README.txt
setup.py
dineshbasiccalculator/__init__.py
dineshbasiccalculator.egg-info/PKG-INFO
dineshbasiccalculator.egg-info/SOURCES.txt
dineshbasiccalculator.egg-info/dependency_links.txt
dineshbasiccalculator.egg-info/top_level.txt